{
  "number": "1386",
  "character": "帮",
  "keyword": "help",
  "requirements": [
    {
      "number": "1223",
      "character": "丰",
      "keyword": "plentiful",
      "requirements": []
    },
    {
      "number": "None",
      "character": "囧阝",
      "keyword": "city walls",
      "requirements": [
        {
          "number": "None",
          "character": "阝",
          "keyword": "pinnacle",
          "requirements": []
        }
      ]
    },
    {
      "number": "410",
      "character": "巾",
      "keyword": "towel",
      "requirements": []
    }
  ]
}