{
  "number": "1418",
  "character": "番",
  "keyword": "try",
  "requirements": [
    {
      "number": "None",
      "character": "釆",
      "keyword": "droppings",
      "requirements": [
        {
          "number": "None",
          "character": "丶",
          "keyword": "a drop of",
          "requirements": []
        },
        {
          "number": "778",
          "character": "米",
          "keyword": "rice",
          "requirements": []
        }
      ]
    },
    {
      "number": "14",
      "character": "田",
      "keyword": "rice field",
      "requirements": []
    }
  ]
}