{
  "number": "1714",
  "character": "霉",
  "keyword": "mildew",
  "requirements": [
    {
      "number": "425",
      "character": "雨",
      "keyword": "rain",
      "requirements": []
    },
    {
      "number": "467",
      "character": "每",
      "keyword": "every",
      "requirements": [
        {
          "number": "None",
          "character": "𠂉",
          "keyword": "reclining",
          "requirements": []
        },
        {
          "number": "105",
          "character": "母",
          "keyword": "mother",
          "requirements": [
            {
              "number": "102",
              "character": "女",
              "keyword": "woman",
              "requirements": []
            }
          ]
        }
      ]
    }
  ]
}