{
  "id": "1781",
  "label": "墙\nwall",
  "requirements": [
    {
      "id": "158",
      "label": "土\nsoil",
      "requirements": []
    },
    {
      "id": "None",
      "label": "丷\nhorns",
      "requirements": [
        {
          "id": "1",
          "label": "一\none",
          "requirements": []
        }
      ]
    },
    {
      "id": "554",
      "label": "回\nreturn",
      "requirements": [
        {
          "id": "None",
          "label": "囗\npent in",
          "requirements": []
        },
        {
          "id": "11",
          "label": "口\nmouth",
          "requirements": []
        }
      ]
    }
  ]
}