{
  "number": "1908",
  "character": "胎",
  "keyword": "fetus",
  "id": "F",
  "requirements": [
    {
      "number": "13",
      "character": "月",
      "keyword": "month",
      "id": "B",
      "requirements": []
    },
    {
      "number": "672",
      "character": "台",
      "keyword": "platform",
      "id": "E",
      "requirements": [
        {
          "number": null,
          "character": "厶",
          "keyword": "elbow",
          "id": "C",
          "requirements": []
        },
        {
          "number": "11",
          "character": "口",
          "keyword": "mouth",
          "id": "D",
          "requirements": []
        }
      ]
    }
  ]
}