{
  "id": "2015",
  "label": "穗\near of grain",
  "requirements": [
    {
      "id": "762",
      "label": "禾\nstanding grain",
      "requirements": []
    },
    {
      "id": "1794",
      "label": "惠\nfavor",
      "requirements": [
        {
          "id": "1",
          "label": "一\none",
          "requirements": []
        },
        {
          "id": "12",
          "label": "日\nday",
          "requirements": []
        },
        {
          "id": "509",
          "label": "虫\ninsect",
          "requirements": []
        },
        {
          "id": "563",
          "label": "心\nheart",
          "requirements": []
        }
      ]
    }
  ]
}