{
  "number": "2296",
  "character": "嗜",
  "keyword": "hanker",
  "requirements": [
    {
      "number": "11",
      "character": "口",
      "keyword": "mouth",
      "requirements": []
    },
    {
      "number": "1029",
      "character": "老",
      "keyword": "old man",
      "requirements": [
        {
          "number": "158",
          "character": "土",
          "keyword": "soil",
          "requirements": []
        },
        {
          "number": "None",
          "character": "丨",
          "keyword": "walking stick",
          "requirements": [
            {
              "number": "1",
              "character": "一",
              "keyword": "one",
              "requirements": []
            }
          ]
        },
        {
          "number": "453",
          "character": "匕",
          "keyword": "ancient spoon",
          "requirements": []
        }
      ]
    },
    {
      "number": "12",
      "character": "日",
      "keyword": "day",
      "requirements": []
    }
  ]
}