{
  "id": "2438",
  "label": "铃\nsmall bell",
  "requirements": [
    {
      "id": "279",
      "label": "金\ngold",
      "requirements": [
        {
          "id": "None",
          "label": "𠆢\numbrella",
          "requirements": []
        },
        {
          "id": "265",
          "label": "王\nking",
          "requirements": [
            {
              "id": "76",
              "label": "工\nwork",
              "requirements": []
            }
          ]
        },
        {
          "id": "None",
          "label": "丶\na drop of",
          "requirements": []
        }
      ]
    },
    {
      "id": "1113",
      "label": "令\norders",
      "requirements": [
        {
          "id": "None",
          "label": "亼\nmeeting",
          "requirements": [
            {
              "id": "None",
              "label": "𠆢\numbrella",
              "requirements": []
            }
          ]
        },
        {
          "id": "None",
          "label": "囧节－艹\nchop",
          "requirements": []
        }
      ]
    }
  ]
}