{
  "number": "2555",
  "character": "辫",
  "keyword": "braid",
  "requirements": [
    {
      "number": "1183",
      "character": "辛",
      "keyword": "peppery",
      "requirements": [
        {
          "number": "444",
          "character": "立",
          "keyword": "standing up",
          "requirements": []
        },
        {
          "number": "10",
          "character": "十",
          "keyword": "ten",
          "requirements": []
        }
      ]
    },
    {
      "number": null,
      "character": "纟",
      "keyword": "thread",
      "requirements": [
        {
          "number": null,
          "character": "厶",
          "keyword": "elbow",
          "requirements": []
        }
      ]
    }
  ]
}