{
  "number": "2892",
  "character": "豫",
  "keyword": "pleased",
  "id": "K",
  "requirements": [
    {
      "number": "1005",
      "character": "予",
      "keyword": "bestow",
      "id": "C",
      "requirements": [
        {
          "number": "1002",
          "character": "矛",
          "keyword": "spear",
          "id": "B",
          "requirements": []
        }
      ]
    },
    {
      "number": "1451",
      "character": "象",
      "keyword": "elephant",
      "id": "J",
      "requirements": [
        {
          "number": "1447",
          "character": "兔",
          "keyword": "rabbit",
          "id": "H",
          "requirements": [
            {
              "number": null,
              "character": "勹",
              "keyword": "bound up",
              "id": "D",
              "requirements": []
            },
            {
              "number": "11",
              "character": "口",
              "keyword": "mouth",
              "id": "E",
              "requirements": []
            },
            {
              "number": "56",
              "character": "儿",
              "keyword": "youngster",
              "id": "F",
              "requirements": []
            },
            {
              "number": null,
              "character": "丶",
              "keyword": "a drop of",
              "id": "G",
              "requirements": []
            }
          ]
        },
        {
          "number": null,
          "character": "豕",
          "keyword": "sow",
          "id": "I",
          "requirements": []
        }
      ]
    }
  ]
}