{
  "number": "36",
  "character": "皂",
  "keyword": "soap",
  "requirements": [
    {
      "number": "34",
      "character": "白",
      "keyword": "white",
      "requirements": [
        {
          "number": "12",
          "character": "日",
          "keyword": "day",
          "requirements": []
        },
        {
          "number": "None",
          "character": "丶",
          "keyword": "a drop of",
          "requirements": []
        }
      ]
    },
    {
      "number": "7",
      "character": "七",
      "keyword": "seven",
      "requirements": []
    }
  ]
}