{
  "order": 1140,
  "hierarchy": {
    "number": "1059",
    "character": "阴",
    "keyword": "Yin",
    "level": "Advanced",
    "filename": "1059_Yin",
    "id": "D",
    "requirements": [
      {
        "number": null,
        "character": "阝",
        "keyword": "pinnacle",
        "level": null,
        "filename": "primitive_pinnacle",
        "id": "B",
        "requirements": []
      },
      {
        "number": "13",
        "character": "月",
        "keyword": "month",
        "level": "Elementary",
        "filename": "13_month",
        "id": "C",
        "requirements": []
      }
    ]
  }
}