{
  "number": "1110",
  "character": "柳",
  "keyword": "willow",
  "id": "F",
  "requirements": [
    {
      "number": "202",
      "character": "木",
      "keyword": "tree",
      "id": "B",
      "requirements": []
    },
    {
      "number": null,
      "character": "囧贸－贝",
      "keyword": "letter opener",
      "id": "E",
      "requirements": [
        {
          "number": null,
          "character": "卩",
          "keyword": "stamp",
          "id": "C",
          "requirements": []
        },
        {
          "number": "83",
          "character": "刀",
          "keyword": "sword",
          "id": "D",
          "requirements": []
        }
      ]
    }
  ]
}