{
  "order": 1304,
  "hierarchy": {
    "number": "1202",
    "character": "壤",
    "keyword": "territory",
    "level": null,
    "filename": "1202_territory",
    "id": "I",
    "requirements": [
      {
        "number": "158",
        "character": "土",
        "keyword": "soil",
        "level": "Medium",
        "filename": "158_soil",
        "id": "B",
        "requirements": []
      },
      {
        "number": "1201",
        "character": "襄",
        "keyword": "aid",
        "level": null,
        "filename": "1201_aid",
        "id": "H",
        "requirements": [
          {
            "number": "400",
            "character": "衣",
            "keyword": "clothing",
            "level": "Elementary",
            "filename": "400_clothing",
            "id": "D",
            "requirements": [
              {
                "number": null,
                "character": "亠",
                "keyword": "top hat",
                "level": null,
                "filename": "primitive_top_hat",
                "id": "C",
                "requirements": []
              }
            ]
          },
          {
            "number": null,
            "character": "吅",
            "keyword": "chatterbox",
            "level": null,
            "filename": "primitive_chatterbox",
            "id": "F",
            "requirements": [
              {
                "number": "11",
                "character": "口",
                "keyword": "mouth",
                "level": "Elementary",
                "filename": "11_mouth",
                "id": "E",
                "requirements": []
              }
            ]
          },
          {
            "number": null,
            "character": "𠀎",
            "keyword": "wire mesh",
            "level": null,
            "filename": "primitive_wire_mesh",
            "id": "G",
            "requirements": []
          }
        ]
      }
    ]
  }
}