{
  "order": 1341,
  "hierarchy": {
    "number": "1235",
    "character": "陆",
    "keyword": "land",
    "level": "Advanced",
    "filename": "1235_-_land",
    "id": "G",
    "requirements": [
      {
        "number": null,
        "character": "阝",
        "keyword": "pinnacle",
        "level": null,
        "filename": "PRIMITIVE_-_pinnacle",
        "id": "B",
        "requirements": []
      },
      {
        "number": "1234",
        "character": "击",
        "keyword": "beat",
        "level": null,
        "filename": "1234_-_beat",
        "id": "F",
        "requirements": [
          {
            "number": null,
            "character": "囧奉－𡗗",
            "keyword": "cornstalk",
            "level": null,
            "filename": "PRIMITIVE_-_cornstalk",
            "id": "D",
            "requirements": [
              {
                "number": "1223",
                "character": "丰",
                "keyword": "plentiful",
                "level": "Advanced",
                "filename": "1223_-_plentiful",
                "id": "C",
                "requirements": []
              }
            ]
          },
          {
            "number": "688",
            "character": "山",
            "keyword": "mountain",
            "level": "Elementary",
            "filename": "688_-_mountain",
            "id": "E",
            "requirements": []
          }
        ]
      }
    ]
  }
}