{
  "order": 1724,
  "hierarchy": {
    "number": "1584",
    "character": "膜",
    "keyword": "membrane",
    "level": null,
    "filename": "1584_membrane",
    "id": "G",
    "requirements": [
      {
        "number": "13",
        "character": "月",
        "keyword": "month",
        "level": "Elementary",
        "filename": "13_month",
        "id": "B",
        "requirements": []
      },
      {
        "number": "231",
        "character": "莫",
        "keyword": "nobody",
        "level": null,
        "filename": "231_nobody",
        "id": "F",
        "requirements": [
          {
            "number": null,
            "character": "艹",
            "keyword": "flower",
            "level": null,
            "filename": "PRIMITIVE_flower",
            "id": "C",
            "requirements": []
          },
          {
            "number": "12",
            "character": "日",
            "keyword": "day",
            "level": "Elementary",
            "filename": "12_day",
            "id": "D",
            "requirements": []
          },
          {
            "number": "113",
            "character": "大",
            "keyword": "large",
            "level": "Elementary",
            "filename": "113_large",
            "id": "E",
            "requirements": []
          }
        ]
      }
    ]
  }
}