{
  "order": 174,
  "hierarchy": {
    "number": "165",
    "character": "哇",
    "keyword": "waaah!",
    "level": null,
    "filename": "165_waaah!",
    "id": "E",
    "requirements": [
      {
        "number": "11",
        "character": "口",
        "keyword": "mouth",
        "level": "Elementary",
        "filename": "11_mouth",
        "id": "B",
        "requirements": []
      },
      {
        "number": null,
        "character": "圭",
        "keyword": "bricks",
        "level": null,
        "filename": "PRIMITIVE_bricks",
        "id": "D",
        "requirements": [
          {
            "number": "158",
            "character": "土",
            "keyword": "soil",
            "level": "Medium",
            "filename": "158_soil",
            "id": "C",
            "requirements": []
          }
        ]
      }
    ]
  }
}