{
  "order": 1969,
  "hierarchy": {
    "number": "1819",
    "character": "慕",
    "keyword": "admire",
    "level": null,
    "filename": "1819_admire",
    "id": "G",
    "requirements": [
      {
        "number": "231",
        "character": "莫",
        "keyword": "nobody",
        "level": null,
        "filename": "231_nobody",
        "id": "E",
        "requirements": [
          {
            "number": null,
            "character": "艹",
            "keyword": "flower",
            "level": null,
            "filename": "primitive_flower",
            "id": "B",
            "requirements": []
          },
          {
            "number": "12",
            "character": "日",
            "keyword": "day",
            "level": "Elementary",
            "filename": "12_day",
            "id": "C",
            "requirements": []
          },
          {
            "number": "113",
            "character": "大",
            "keyword": "large",
            "level": "Elementary",
            "filename": "113_large",
            "id": "D",
            "requirements": []
          }
        ]
      },
      {
        "number": "563",
        "character": "心",
        "keyword": "heart",
        "level": "Medium",
        "filename": "563_heart",
        "id": "F",
        "requirements": []
      }
    ]
  }
}