{
  "number": "2081",
  "character": "侨",
  "keyword": "live abroad",
  "level": null,
  "filename": "2081_live_abroad",
  "id": "H",
  "requirements": [
    {
      "number": "793",
      "character": "人",
      "keyword": "person",
      "level": "Elementary",
      "filename": "793_person",
      "id": "B",
      "requirements": []
    },
    {
      "number": "441",
      "character": "乔",
      "keyword": "pretend",
      "level": null,
      "filename": "441_pretend",
      "id": "G",
      "requirements": [
        {
          "number": null,
          "character": "囧介－𠆢",
          "keyword": "crutches",
          "level": null,
          "filename": "extra_crutches",
          "id": "C",
          "requirements": []
        },
        {
          "number": "440",
          "character": "夭",
          "keyword": "die young",
          "level": null,
          "filename": "440_die_young",
          "id": "F",
          "requirements": [
            {
              "number": "113",
              "character": "大",
              "keyword": "large",
              "level": "Elementary",
              "filename": "113_large",
              "id": "D",
              "requirements": []
            },
            {
              "number": null,
              "character": "丶",
              "keyword": "a drop of",
              "level": null,
              "filename": "extra_a_drop_of",
              "id": "E",
              "requirements": []
            }
          ]
        }
      ]
    }
  ]
}