{
  "number": "2275",
  "character": "蝉",
  "keyword": "cicada",
  "level": null,
  "id": "H",
  "requirements": [
    {
      "number": "509",
      "character": "虫",
      "keyword": "insect",
      "level": "Medium",
      "id": "B",
      "requirements": []
    },
    {
      "number": "1018",
      "character": "单",
      "keyword": "list",
      "level": "Medium",
      "id": "G",
      "requirements": [
        {
          "number": null,
          "character": "丷",
          "keyword": "horns",
          "level": null,
          "id": "D",
          "requirements": [
            {
              "number": "1",
              "character": "一",
              "keyword": "one",
              "level": "Elementary",
              "id": "C",
              "requirements": []
            }
          ]
        },
        {
          "number": "14",
          "character": "田",
          "keyword": "rice field",
          "level": "Medium",
          "id": "E",
          "requirements": []
        },
        {
          "number": "10",
          "character": "十",
          "keyword": "ten",
          "level": "Elementary",
          "id": "F",
          "requirements": []
        }
      ]
    }
  ]
}