{
  "order": 2511,
  "hierarchy": {
    "number": "2342",
    "character": "障",
    "keyword": "barrier",
    "level": null,
    "filename": "2342_barrier",
    "id": "H",
    "requirements": [
      {
        "number": null,
        "character": "阝",
        "keyword": "pinnacle",
        "level": null,
        "filename": "primitive_pinnacle",
        "id": "B",
        "requirements": []
      },
      {
        "number": "447",
        "character": "章",
        "keyword": "chapter",
        "level": "Advanced",
        "filename": "447_chapter",
        "id": "G",
        "requirements": [
          {
            "number": "26",
            "character": "早",
            "keyword": "early",
            "level": "Elementary",
            "filename": "26_early",
            "id": "E",
            "requirements": [
              {
                "number": "12",
                "character": "日",
                "keyword": "day",
                "level": "Elementary",
                "filename": "12_day",
                "id": "C",
                "requirements": []
              },
              {
                "number": "10",
                "character": "十",
                "keyword": "ten",
                "level": "Elementary",
                "filename": "10_ten",
                "id": "D",
                "requirements": []
              }
            ]
          },
          {
            "number": "444",
            "character": "立",
            "keyword": "standing up",
            "level": "Advanced",
            "filename": "444_standing_up",
            "id": "F",
            "requirements": []
          }
        ]
      }
    ]
  }
}