{
  "number": "2645",
  "character": "竿",
  "keyword": "pole",
  "level": null,
  "filename": "2645_pole",
  "id": "E",
  "requirements": [
    {
      "number": "786",
      "character": "竹",
      "keyword": "bamboo",
      "level": "Advanced",
      "filename": "786_bamboo",
      "id": "C",
      "requirements": [
        {
          "number": "90",
          "character": "丁",
          "keyword": "fourth",
          "level": null,
          "filename": "90_fourth",
          "id": "B",
          "requirements": []
        }
      ]
    },
    {
      "number": "1277",
      "character": "干",
      "keyword": "dry",
      "level": "Elementary",
      "filename": "1277_dry",
      "id": "D",
      "requirements": []
    }
  ]
}