{
  "order": 2899,
  "hierarchy": {
    "number": "2707",
    "character": "趁",
    "keyword": "take advantage of",
    "level": null,
    "filename": "2707_take_advantage_of",
    "id": "K",
    "requirements": [
      {
        "number": null,
        "character": "㐱",
        "keyword": "cocktail",
        "level": null,
        "filename": "PRIMITIVE_cocktail",
        "id": "D",
        "requirements": [
          {
            "number": null,
            "character": "𠆢",
            "keyword": "umbrella",
            "level": null,
            "filename": "PRIMITIVE_umbrella",
            "id": "B",
            "requirements": []
          },
          {
            "number": null,
            "character": "彡",
            "keyword": "rooster tail",
            "level": null,
            "filename": "PRIMITIVE_rooster_tail",
            "id": "C",
            "requirements": []
          }
        ]
      },
      {
        "number": "391",
        "character": "走",
        "keyword": "walk",
        "level": "Elementary",
        "filename": "391_walk",
        "id": "J",
        "requirements": [
          {
            "number": null,
            "character": "囧走－十",
            "keyword": "mending",
            "level": null,
            "filename": "PRIMITIVE_mending",
            "id": "H",
            "requirements": [
              {
                "number": "387",
                "character": "正",
                "keyword": "correct",
                "level": "Elementary",
                "filename": "387_correct",
                "id": "G",
                "requirements": [
                  {
                    "number": "1",
                    "character": "一",
                    "keyword": "one",
                    "level": "Elementary",
                    "filename": "1_one",
                    "id": "E",
                    "requirements": []
                  },
                  {
                    "number": "379",
                    "character": "止",
                    "keyword": "stop",
                    "level": "Medium",
                    "filename": "379_stop",
                    "id": "F",
                    "requirements": []
                  }
                ]
              }
            ]
          },
          {
            "number": "158",
            "character": "土",
            "keyword": "soil",
            "level": "Medium",
            "filename": "158_soil",
            "id": "I",
            "requirements": []
          }
        ]
      }
    ]
  }
}