{
  "number": "2711",
  "character": "萨",
  "keyword": "Samoa",
  "level": null,
  "id": "G",
  "requirements": [
    {
      "number": null,
      "character": "艹",
      "keyword": "flower",
      "level": null,
      "id": "B",
      "requirements": []
    },
    {
      "number": null,
      "character": "阝",
      "keyword": "pinnacle",
      "level": null,
      "id": "C",
      "requirements": []
    },
    {
      "number": "1312",
      "character": "产",
      "keyword": "products",
      "level": "Medium",
      "id": "F",
      "requirements": [
        {
          "number": "444",
          "character": "立",
          "keyword": "standing up",
          "level": "Advanced",
          "id": "D",
          "requirements": []
        },
        {
          "number": "121",
          "character": "厂",
          "keyword": "factory",
          "level": "Medium",
          "id": "E",
          "requirements": []
        }
      ]
    }
  ]
}