{
  "number": "2786",
  "character": "遍",
  "keyword": "everywhere",
  "id": "H",
  "requirements": [
    {
      "number": "1367",
      "character": "扁",
      "keyword": "flat",
      "id": "F",
      "requirements": [
        {
          "number": null,
          "character": "冊",
          "keyword": "tome",
          "id": "B",
          "requirements": []
        },
        {
          "number": "896",
          "character": "户",
          "keyword": "door",
          "id": "E",
          "requirements": [
            {
              "number": null,
              "character": "丶",
              "keyword": "a drop of",
              "id": "C",
              "requirements": []
            },
            {
              "number": "882",
              "character": "尸",
              "keyword": "corpse",
              "id": "D",
              "requirements": []
            }
          ]
        }
      ]
    },
    {
      "number": null,
      "character": "辶",
      "keyword": "road",
      "id": "G",
      "requirements": []
    }
  ]
}