{
  "order": 3014,
  "hierarchy": {
    "number": "2820",
    "character": "舶",
    "keyword": "liner",
    "level": null,
    "filename": "2820_-_liner",
    "id": "I",
    "requirements": [
      {
        "number": "1394",
        "character": "舟",
        "keyword": "boat",
        "level": null,
        "filename": "1394_-_boat",
        "id": "E",
        "requirements": [
          {
            "number": null,
            "character": "丶",
            "keyword": "a drop of",
            "level": null,
            "filename": "PRIMITIVE_-_a_drop_of",
            "id": "B",
            "requirements": []
          },
          {
            "number": null,
            "character": "冂",
            "keyword": "hood",
            "level": null,
            "filename": "PRIMITIVE_-_hood",
            "id": "D",
            "requirements": [
              {
                "number": "57",
                "character": "几",
                "keyword": "how many?",
                "level": "Elementary",
                "filename": "57_-_how_many",
                "id": "C",
                "requirements": []
              }
            ]
          }
        ]
      },
      {
        "number": "34",
        "character": "白",
        "keyword": "white",
        "level": "Elementary",
        "filename": "34_-_white",
        "id": "H",
        "requirements": [
          {
            "number": "12",
            "character": "日",
            "keyword": "day",
            "level": "Elementary",
            "filename": "12_-_day",
            "id": "F",
            "requirements": []
          },
          {
            "number": null,
            "character": "丶",
            "keyword": "a drop of",
            "level": null,
            "filename": "PRIMITIVE_-_a_drop_of",
            "id": "G",
            "requirements": []
          }
        ]
      }
    ]
  }
}