{
  "order": 3049,
  "hierarchy": {
    "number": "2854",
    "character": "喂",
    "keyword": "Hello...",
    "level": null,
    "filename": "2854_Hello...",
    "id": "F",
    "requirements": [
      {
        "number": "11",
        "character": "口",
        "keyword": "mouth",
        "level": "Elementary",
        "filename": "11_mouth",
        "id": "B",
        "requirements": []
      },
      {
        "number": "2853",
        "character": "畏",
        "keyword": "be afraid of",
        "level": null,
        "filename": "2853_be_afraid_of",
        "id": "E",
        "requirements": [
          {
            "number": "14",
            "character": "田",
            "keyword": "rice field",
            "level": "Medium",
            "filename": "14_rice_field",
            "id": "C",
            "requirements": []
          },
          {
            "number": null,
            "character": "囧丧－十－丷",
            "keyword": "barrette",
            "level": null,
            "filename": "primitive_barrette",
            "id": "D",
            "requirements": []
          }
        ]
      }
    ]
  }
}