{
  "order": 28,
  "hierarchy": {
    "number": "29",
    "character": "胃",
    "keyword": "stomach",
    "level": "Advanced",
    "filename": "29_stomach",
    "id": "D",
    "requirements": [
      {
        "number": "13",
        "character": "月",
        "keyword": "month",
        "level": "Elementary",
        "filename": "13_month",
        "id": "B",
        "requirements": []
      },
      {
        "number": "14",
        "character": "田",
        "keyword": "rice field",
        "level": "Medium",
        "filename": "14_rice_field",
        "id": "C",
        "requirements": []
      }
    ]
  }
}