{
  "order": 29,
  "hierarchy": {
    "number": "30",
    "character": "旦",
    "keyword": "daybreak",
    "level": "Medium",
    "filename": "30_-_daybreak",
    "id": "D",
    "requirements": [
      {
        "number": "12",
        "character": "日",
        "keyword": "day",
        "level": "Elementary",
        "filename": "12_-_day",
        "id": "B",
        "requirements": []
      },
      {
        "number": "1",
        "character": "一",
        "keyword": "one",
        "level": "Elementary",
        "filename": "1_-_one",
        "id": "C",
        "requirements": []
      }
    ]
  }
}