{
  "number": "54",
  "character": "贞",
  "keyword": "chaste",
  "level": null,
  "id": "I",
  "requirements": [
    {
      "number": "52",
      "character": "贝",
      "keyword": "shellfish",
      "level": "Medium",
      "id": "D",
      "requirements": [
        {
          "number": "15",
          "character": "目",
          "keyword": "eye",
          "level": "Medium",
          "id": "B",
          "requirements": []
        },
        {
          "number": null,
          "character": "囧只－口",
          "keyword": "animal legs",
          "level": null,
          "id": "C",
          "requirements": []
        }
      ]
    },
    {
      "number": "43",
      "character": "卜",
      "keyword": "divination",
      "level": null,
      "id": "H",
      "requirements": [
        {
          "number": null,
          "character": "丨",
          "keyword": "walking stick",
          "level": null,
          "id": "F",
          "requirements": [
            {
              "number": "1",
              "character": "一",
              "keyword": "one",
              "level": "Elementary",
              "id": "E",
              "requirements": []
            }
          ]
        },
        {
          "number": null,
          "character": "丶",
          "keyword": "a drop of",
          "level": null,
          "id": "G",
          "requirements": []
        }
      ]
    }
  ]
}