{
  "order": 734,
  "hierarchy": {
    "number": "678",
    "character": "至",
    "keyword": "until",
    "level": "Advanced",
    "filename": "678_-_until",
    "id": "F",
    "requirements": [
      {
        "number": null,
        "character": "囧会－亼",
        "keyword": "wall",
        "level": null,
        "filename": "PRIMITIVE_-_wall",
        "id": "D",
        "requirements": [
          {
            "number": null,
            "character": "厶",
            "keyword": "elbow",
            "level": null,
            "filename": "PRIMITIVE_-_elbow",
            "id": "B",
            "requirements": []
          },
          {
            "number": "1",
            "character": "一",
            "keyword": "one",
            "level": "Elementary",
            "filename": "1_-_one",
            "id": "C",
            "requirements": []
          }
        ]
      },
      {
        "number": "158",
        "character": "土",
        "keyword": "soil",
        "level": "Medium",
        "filename": "158_-_soil",
        "id": "E",
        "requirements": []
      }
    ]
  }
}