{
  "number": "678",
  "character": "至",
  "keyword": "until",
  "id": "F",
  "requirements": [
    {
      "number": null,
      "character": "囧会－亼",
      "keyword": "wall",
      "id": "D",
      "requirements": [
        {
          "number": null,
          "character": "厶",
          "keyword": "elbow",
          "id": "B",
          "requirements": []
        },
        {
          "number": "1",
          "character": "一",
          "keyword": "one",
          "id": "C",
          "requirements": []
        }
      ]
    },
    {
      "number": "158",
      "character": "土",
      "keyword": "soil",
      "id": "E",
      "requirements": []
    }
  ]
}