{
  "number": "947",
  "character": "当",
  "keyword": "work as",
  "level": "Elementary",
  "filename": "947_work_as",
  "id": "E",
  "requirements": [
    {
      "number": "109",
      "character": "小",
      "keyword": "small",
      "level": "Elementary",
      "filename": "109_small",
      "id": "C",
      "requirements": [
        {
          "number": null,
          "character": "丶",
          "keyword": "a drop of",
          "level": null,
          "filename": "extra_a_drop_of",
          "id": "B",
          "requirements": []
        }
      ]
    },
    {
      "number": null,
      "character": "彐",
      "keyword": "broom",
      "level": null,
      "filename": "extra_broom",
      "id": "D",
      "requirements": []
    }
  ]
}